visionary/__init__.py
visionary/client.py
visionary/compat.py
visionary/exceptions.py
visionary/features.py
visionary/response.py
visionary-1.2.0.dist-info/DESCRIPTION.rst
visionary-1.2.0.dist-info/METADATA
visionary-1.2.0.dist-info/RECORD
visionary-1.2.0.dist-info/WHEEL
visionary-1.2.0.dist-info/metadata.json
visionary-1.2.0.dist-info/top_level.txt
