Metadata-Version: 2.0
Name: visionary
Version: 1.2.0
Summary: Client library for Google Cloud Vision API
Home-page: https://github.com/shafaua/visionary
Author: Igor Gumenyuk
Author-email: UNKNOWN
License: Apache 2.0
Platform: UNKNOWN
Classifier: Development Status :: 4 - Beta
Classifier: Intended Audience :: Developers
Classifier: Natural Language :: English
Classifier: License :: OSI Approved :: Apache Software License
Classifier: Programming Language :: Python :: Implementation :: CPython
Classifier: Programming Language :: Python :: Implementation :: PyPy
Requires-Dist: requests (<3.0.0)
